{
  "generated_at": "2026-07-11T23:47:22.223956+00:00",
  "count": 2,
  "items": [
    {
      "id": "0986a3e4c5b0",
      "title": "iPhone 17 Pro Max用スマホリング探しの旅。辿り着いたのはシリコングリップだった(ギズモード・ジャパン)",
      "summary": "長い旅路でした。\n\n昨年末に購入したiPhone 17 Pro Max。自分にとっては人生初のPro Maxモデルで、カメラ性能もディスプレイの大きさにも満足しています。ただし「持ちづらい」という点を",
      "url": "https://news.yahoo.co.jp/articles/60c13bf45aca52cbaa5e959712ac039b8234be22?source=rss",
      "source": "news.yahoo.co.jp",
      "published_at": "2026-07-11T11:30:02+00:00",
      "badges": [
        "新着"
      ]
    },
    {
      "id": "3a4c015f4b05",
      "title": "【そろそろ要決断】一部カラーが在庫切れのiPhone Air、最新iPhoneがこの価格はほぼラストチャンス!?(アスキー)",
      "summary": "先行セール時からAmazonプライムデーで目玉となっている「iPhone Air」。 \n　詳しくは、以下の記事も参照いただきたいが（「【割引なら買い】編集部のiPhone Airユーザーが語る「iP",
      "url": "https://news.yahoo.co.jp/articles/39584150c266840b140adbaaa236a20e27cffa68?source=rss",
      "source": "news.yahoo.co.jp",
      "published_at": "2026-07-11T05:30:00+00:00",
      "badges": [
        "新着",
        "値下げ"
      ]
    }
  ]
}